cakemail_mcp/__init__.py
cakemail_mcp/__main__.py
cakemail_mcp/config.py
cakemail_mcp/errors.py
cakemail_mcp/openapi.json
cakemail_mcp/openapi_repository.py
cakemail_mcp/server.py
cakemail_api_docs_mcp-0.1.2.dist-info/METADATA
cakemail_api_docs_mcp-0.1.2.dist-info/WHEEL
cakemail_api_docs_mcp-0.1.2.dist-info/entry_points.txt
cakemail_api_docs_mcp-0.1.2.dist-info/licenses/LICENSE
cakemail_api_docs_mcp-0.1.2.dist-info/RECORD
