Metadata-Version: 2.4
Name: cakemail-api-docs-mcp
Version: 0.1.2
Summary: MCP server exposing Cakemail API documentation to AI agents
Project-URL: Homepage, https://github.com/cakemail/cakemail-api-documentation-mcp
Project-URL: Documentation, https://github.com/cakemail/cakemail-api-documentation-mcp#readme
Project-URL: Repository, https://github.com/cakemail/cakemail-api-documentation-mcp
Project-URL: Issues, https://github.com/cakemail/cakemail-api-documentation-mcp/issues
Author-email: Cakemail <support@cakemail.com>
License: MIT
License-File: LICENSE
Keywords: ai,api,cakemail,mcp,model-context-protocol,openapi
Classifier: Development Status :: 3 - Alpha
Classifier: Intended Audience :: Developers
Classifier: License :: OSI Approved :: MIT License
Classifier: Programming Language :: Python :: 3
Classifier: Programming Language :: Python :: 3.11
Classifier: Programming Language :: Python :: 3.12
Requires-Python: >=3.11
Requires-Dist: fastmcp>=0.2.0
Requires-Dist: httpx>=0.27.0
Requires-Dist: python-dotenv>=1.0.0
Provides-Extra: dev
Requires-Dist: black>=24.0.0; extra == 'dev'
Requires-Dist: mypy>=1.8.0; extra == 'dev'
Requires-Dist: pytest-cov>=4.1.0; extra == 'dev'
Requires-Dist: pytest>=8.0.0; extra == 'dev'
Requires-Dist: ruff>=0.2.0; extra == 'dev'
Requires-Dist: twine>=5.0.0; extra == 'dev'
